{
  "schema_version": 1,
  "generated_at": "2026-06-11T19:50:15.091Z",
  "scan_duration_ms": 5288,
  "errors": [],
  "stats": {
    "poly_markets_scanned": 1114,
    "kalshi_markets_scanned": 1342,
    "candidates_pre_filter": 27,
    "tier1_count": 0,
    "tier2_count": 2,
    "tier3_count": 7,
    "pre_cap_tier1": 0,
    "pre_cap_tier2": 2,
    "pre_cap_tier3": 7,
    "per_tier_cap": 50,
    "history_lookback_days": 14
  },
  "opportunities": [
    {
      "id": "pass1-poly-sum-world-cup-winner-overpriced",
      "tier": 2,
      "type": "poly_sum_violation",
      "summary": "Polymarket negRisk: World Cup Winner  — 48 legs sum to 1.044 (4.4pp overpriced; buy-all-NO)",
      "underlying": "OTHER",
      "resolution_date": "2026-07-20",
      "resolution_type": "monthly",
      "legs": [
        {
          "platform": "polymarket",
          "market_id": "558934",
          "market_url": "https://polymarket.com/event/world-cup-winner/will-spain-win-the-2026-fifa-world-cup-963",
          "side": "YES",
          "price": 0.1695,
          "depth_usd_at_price": 328672,
          "last_trade_at": "2026-06-11T19:39:05.098218Z",
          "volume_24h_usd": 2783193
        },
        {
          "platform": "polymarket",
          "market_id": "558957",
          "market_url": "https://polymarket.com/event/world-cup-winner/will-new-zealand-win-the-2026-fifa-world-cup-635",
          "side": "YES",
          "price": 0.0005,
          "depth_usd_at_price": 4628820,
          "last_trade_at": "2026-06-11T19:38:21.760478Z",
          "volume_24h_usd": 91045
        },
        {
          "platform": "polymarket",
          "market_id": "558974",
          "market_url": "https://polymarket.com/event/world-cup-winner/will-switzerland-win-the-2026-fifa-world-cup",
          "side": "YES",
          "price": 0.0125,
          "depth_usd_at_price": 596913,
          "last_trade_at": "2026-06-11T19:48:05.613574Z",
          "volume_24h_usd": 3487942
        },
        {
          "platform": "polymarket",
          "market_id": "558935",
          "market_url": "https://polymarket.com/event/world-cup-winner/will-england-win-the-2026-fifa-world-cup-937",
          "side": "YES",
          "price": 0.1055,
          "depth_usd_at_price": 493309,
          "last_trade_at": "2026-06-11T19:37:31.904168Z",
          "volume_24h_usd": 2377460
        },
        {
          "platform": "polymarket",
          "market_id": "558936",
          "market_url": "https://polymarket.com/event/world-cup-winner/will-france-win-the-2026-fifa-world-cup-924",
          "side": "YES",
          "price": 0.1605,
          "depth_usd_at_price": 396409,
          "last_trade_at": "2026-06-11T19:47:28.846996Z",
          "volume_24h_usd": 2431396
        },
        {
          "platform": "polymarket",
          "market_id": "558961",
          "market_url": "https://polymarket.com/event/world-cup-winner/will-south-korea-win-the-2026-fifa-world-cup-485",
          "side": "YES",
          "price": 0.0025,
          "depth_usd_at_price": 1186486,
          "last_trade_at": "2026-06-11T19:47:48.371842Z",
          "volume_24h_usd": 3359672
        },
        {
          "platform": "polymarket",
          "market_id": "558977",
          "market_url": "https://polymarket.com/event/world-cup-winner/will-haiti-win-the-2026-fifa-world-cup",
          "side": "YES",
          "price": 0.0005,
          "depth_usd_at_price": 4558050,
          "last_trade_at": "2026-06-11T19:47:48.395708Z",
          "volume_24h_usd": 132651
        },
        {
          "platform": "polymarket",
          "market_id": "558937",
          "market_url": "https://polymarket.com/event/world-cup-winner/will-brazil-win-the-2026-fifa-world-cup-183",
          "side": "YES",
          "price": 0.0865,
          "depth_usd_at_price": 416727,
          "last_trade_at": "2026-06-11T19:41:03.91072Z",
          "volume_24h_usd": 2403380
        },
        {
          "platform": "polymarket",
          "market_id": "558962",
          "market_url": "https://polymarket.com/event/world-cup-winner/will-jordan-win-the-2026-fifa-world-cup-233",
          "side": "YES",
          "price": 0.0005,
          "depth_usd_at_price": 4582896,
          "last_trade_at": "2026-06-11T19:42:11.622454Z",
          "volume_24h_usd": 213958
        },
        {
          "platform": "polymarket",
          "market_id": "558978",
          "market_url": "https://polymarket.com/event/world-cup-winner/will-curaao-win-the-2026-fifa-world-cup",
          "side": "YES",
          "price": 0.0005,
          "depth_usd_at_price": 4511058,
          "last_trade_at": "2026-06-11T19:42:25.611388Z",
          "volume_24h_usd": 344135
        },
        {
          "platform": "polymarket",
          "market_id": "558938",
          "market_url": "https://polymarket.com/event/world-cup-winner/will-argentina-win-the-2026-fifa-world-cup-245",
          "side": "YES",
          "price": 0.0885,
          "depth_usd_at_price": 321298,
          "last_trade_at": "2026-06-11T19:38:43.219682Z",
          "volume_24h_usd": 3475698
        },
        {
          "platform": "polymarket",
          "market_id": "558939",
          "market_url": "https://polymarket.com/event/world-cup-winner/will-germany-win-the-2026-fifa-world-cup-467",
          "side": "YES",
          "price": 0.0515,
          "depth_usd_at_price": 629390,
          "last_trade_at": "2026-06-11T19:39:57.894332Z",
          "volume_24h_usd": 2602781
        },
        {
          "platform": "polymarket",
          "market_id": "558947",
          "market_url": "https://polymarket.com/event/world-cup-winner/will-colombia-win-the-2026-fifa-world-cup-734",
          "side": "YES",
          "price": 0.0175,
          "depth_usd_at_price": 778687,
          "last_trade_at": "2026-06-11T19:42:30.559941Z",
          "volume_24h_usd": 5237338
        },
        {
          "platform": "polymarket",
          "market_id": "558959",
          "market_url": "https://polymarket.com/event/world-cup-winner/will-iran-win-the-2026-fifa-world-cup-788",
          "side": "YES",
          "price": 0.0015,
          "depth_usd_at_price": 2640845,
          "last_trade_at": "2026-06-11T19:42:43.906641Z",
          "volume_24h_usd": 2946481
        },
        {
          "platform": "polymarket",
          "market_id": "558940",
          "market_url": "https://polymarket.com/event/world-cup-winner/will-portugal-win-the-2026-fifa-world-cup-912",
          "side": "YES",
          "price": 0.1115,
          "depth_usd_at_price": 137070,
          "last_trade_at": "2026-06-11T19:40:20.262355Z",
          "volume_24h_usd": 3369388
        },
        {
          "platform": "polymarket",
          "market_id": "558967",
          "market_url": "https://polymarket.com/event/world-cup-winner/will-ghana-win-the-2026-fifa-world-cup",
          "side": "YES",
          "price": 0.0015,
          "depth_usd_at_price": 3886708,
          "last_trade_at": "2026-06-11T19:42:34.673485Z",
          "volume_24h_usd": 2488639
        },
        {
          "platform": "polymarket",
          "market_id": "558941",
          "market_url": "https://polymarket.com/event/world-cup-winner/will-netherlands-win-the-2026-fifa-world-cup-739",
          "side": "YES",
          "price": 0.0475,
          "depth_usd_at_price": 478694,
          "last_trade_at": "2026-06-11T19:38:28.472137Z",
          "volume_24h_usd": 3632672
        },
        {
          "platform": "polymarket",
          "market_id": "558969",
          "market_url": "https://polymarket.com/event/world-cup-winner/will-algeria-win-the-2026-fifa-world-cup",
          "side": "YES",
          "price": 0.0015,
          "depth_usd_at_price": 2479389,
          "last_trade_at": "2026-06-11T19:40:09.34006Z",
          "volume_24h_usd": 3251162
        },
        {
          "platform": "polymarket",
          "market_id": "558983",
          "market_url": "https://polymarket.com/event/world-cup-winner/will-bosnia-herzegovina-win-the-2026-fifa-world-cup",
          "side": "YES",
          "price": 0.0015,
          "depth_usd_at_price": 3396761,
          "last_trade_at": "2026-06-11T19:38:03.106895Z",
          "volume_24h_usd": 3757854
        },
        {
          "platform": "polymarket",
          "market_id": "558943",
          "market_url": "https://polymarket.com/event/world-cup-winner/will-usa-win-the-2026-fifa-world-cup-467",
          "side": "YES",
          "price": 0.0115,
          "depth_usd_at_price": 1534492,
          "last_trade_at": "2026-06-11T19:37:39.722551Z",
          "volume_24h_usd": 2912701
        },
        {
          "platform": "polymarket",
          "market_id": "558952",
          "market_url": "https://polymarket.com/event/world-cup-winner/will-canada-win-the-2026-fifa-world-cup-755",
          "side": "YES",
          "price": 0.0035,
          "depth_usd_at_price": 1802468,
          "last_trade_at": "2026-06-11T19:38:18.520478Z",
          "volume_24h_usd": 2790618
        },
        {
          "platform": "polymarket",
          "market_id": "558985",
          "market_url": "https://polymarket.com/event/world-cup-winner/will-turkiye-win-the-2026-fifa-world-cup",
          "side": "YES",
          "price": 0.0105,
          "depth_usd_at_price": 504472,
          "last_trade_at": "2026-06-11T19:42:47.129026Z",
          "volume_24h_usd": 2938678
        },
        {
          "platform": "polymarket",
          "market_id": "558944",
          "market_url": "https://polymarket.com/event/world-cup-winner/will-uruguay-win-the-2026-fifa-world-cup-932",
          "side": "YES",
          "price": 0.0095,
          "depth_usd_at_price": 2546894,
          "last_trade_at": "2026-06-11T19:38:21.671213Z",
          "volume_24h_usd": 3245606
        },
        {
          "platform": "polymarket",
          "market_id": "558945",
          "market_url": "https://polymarket.com/event/world-cup-winner/will-mexico-win-the-2026-fifa-world-cup-529",
          "side": "YES",
          "price": 0.0195,
          "depth_usd_at_price": 396342,
          "last_trade_at": "2026-06-11T19:42:20.606289Z",
          "volume_24h_usd": 4666027
        },
        {
          "platform": "polymarket",
          "market_id": "558956",
          "market_url": "https://polymarket.com/event/world-cup-winner/will-paraguay-win-the-2026-fifa-world-cup-967",
          "side": "YES",
          "price": 0.0015,
          "depth_usd_at_price": 1822361,
          "last_trade_at": "2026-06-11T19:41:56.818375Z",
          "volume_24h_usd": 5467054
        },
        {
          "platform": "polymarket",
          "market_id": "558973",
          "market_url": "https://polymarket.com/event/world-cup-winner/will-scotland-win-the-2026-fifa-world-cup",
          "side": "YES",
          "price": 0.0025,
          "depth_usd_at_price": 3594840,
          "last_trade_at": "2026-06-11T19:48:41.782627Z",
          "volume_24h_usd": 3722974
        },
        {
          "platform": "polymarket",
          "market_id": "558949",
          "market_url": "https://polymarket.com/event/world-cup-winner/will-japan-win-the-2026-fifa-world-cup-112",
          "side": "YES",
          "price": 0.0175,
          "depth_usd_at_price": 464094,
          "last_trade_at": "2026-06-11T19:39:49.835536Z",
          "volume_24h_usd": 3282871
        },
        {
          "platform": "polymarket",
          "market_id": "558951",
          "market_url": "https://polymarket.com/event/world-cup-winner/will-norway-win-the-2026-fifa-world-cup-893",
          "side": "YES",
          "price": 0.0235,
          "depth_usd_at_price": 501789,
          "last_trade_at": "2026-06-11T19:39:49.217772Z",
          "volume_24h_usd": 4199053
        },
        {
          "platform": "polymarket",
          "market_id": "558954",
          "market_url": "https://polymarket.com/event/world-cup-winner/will-tunisia-win-the-2026-fifa-world-cup-165",
          "side": "YES",
          "price": 0.0005,
          "depth_usd_at_price": 3829005,
          "last_trade_at": "2026-06-11T19:42:44.769014Z",
          "volume_24h_usd": 202643
        },
        {
          "platform": "polymarket",
          "market_id": "558955",
          "market_url": "https://polymarket.com/event/world-cup-winner/will-ecuador-win-the-2026-fifa-world-cup-986",
          "side": "YES",
          "price": 0.0085,
          "depth_usd_at_price": 911742,
          "last_trade_at": "2026-06-11T19:41:46.783093Z",
          "volume_24h_usd": 3807285
        },
        {
          "platform": "polymarket",
          "market_id": "558960",
          "market_url": "https://polymarket.com/event/world-cup-winner/will-uzbekistan-win-the-2026-fifa-world-cup-773",
          "side": "YES",
          "price": 0.0005,
          "depth_usd_at_price": 3206587,
          "last_trade_at": "2026-06-11T19:39:24.393281Z",
          "volume_24h_usd": 298262
        },
        {
          "platform": "polymarket",
          "market_id": "558963",
          "market_url": "https://polymarket.com/event/world-cup-winner/will-morocco-win-the-2026-fifa-world-cup-464",
          "side": "YES",
          "price": 0.0165,
          "depth_usd_at_price": 224992,
          "last_trade_at": "2026-06-11T19:38:01.973602Z",
          "volume_24h_usd": 3719843
        },
        {
          "platform": "polymarket",
          "market_id": "558979",
          "market_url": "https://polymarket.com/event/world-cup-winner/will-team-z-win-the-2026-fifa-world-cup-316",
          "side": "YES",
          "price": 0.0005,
          "depth_usd_at_price": 4560746,
          "last_trade_at": "2026-06-11T19:42:38.694508Z",
          "volume_24h_usd": 120739
        },
        {
          "platform": "polymarket",
          "market_id": "558982",
          "market_url": "https://polymarket.com/event/world-cup-winner/will-iraq-win-the-2026-fifa-world-cup",
          "side": "YES",
          "price": 0.0005,
          "depth_usd_at_price": 4612916,
          "last_trade_at": "2026-06-11T19:47:38.022674Z",
          "volume_24h_usd": 379253
        },
        {
          "platform": "polymarket",
          "market_id": "558964",
          "market_url": "https://polymarket.com/event/world-cup-winner/will-south-africa-win-the-2026-fifa-world-cup",
          "side": "YES",
          "price": 0.0005,
          "depth_usd_at_price": 2504743,
          "last_trade_at": "2026-06-11T19:42:34.73042Z",
          "volume_24h_usd": 623890
        },
        {
          "platform": "polymarket",
          "market_id": "558965",
          "market_url": "https://polymarket.com/event/world-cup-winner/will-senegal-win-the-2026-fifa-world-cup",
          "side": "YES",
          "price": 0.0065,
          "depth_usd_at_price": 1220656,
          "last_trade_at": "2026-06-11T19:42:43.695489Z",
          "volume_24h_usd": 2654238
        },
        {
          "platform": "polymarket",
          "market_id": "558966",
          "market_url": "https://polymarket.com/event/world-cup-winner/will-ivory-coast-win-the-2026-fifa-world-cup",
          "side": "YES",
          "price": 0.0035,
          "depth_usd_at_price": 1273730,
          "last_trade_at": "2026-06-11T19:48:37.978077Z",
          "volume_24h_usd": 3561801
        },
        {
          "platform": "polymarket",
          "market_id": "558981",
          "market_url": "https://polymarket.com/event/world-cup-winner/will-congo-dr-win-the-2026-fifa-world-cup",
          "side": "YES",
          "price": 0.0015,
          "depth_usd_at_price": 2378295,
          "last_trade_at": "2026-06-11T19:38:39.843535Z",
          "volume_24h_usd": 2238660
        },
        {
          "platform": "polymarket",
          "market_id": "558970",
          "market_url": "https://polymarket.com/event/world-cup-winner/will-cape-verde-win-the-2026-fifa-world-cup",
          "side": "YES",
          "price": 0.0005,
          "depth_usd_at_price": 4410119,
          "last_trade_at": "2026-06-11T19:48:20.600663Z",
          "volume_24h_usd": 166347
        },
        {
          "platform": "polymarket",
          "market_id": "558984",
          "market_url": "https://polymarket.com/event/world-cup-winner/will-czechia-win-the-2026-fifa-world-cup",
          "side": "YES",
          "price": 0.0015,
          "depth_usd_at_price": 2728319,
          "last_trade_at": "2026-06-11T19:38:45.758027Z",
          "volume_24h_usd": 7687520
        },
        {
          "platform": "polymarket",
          "market_id": "558971",
          "market_url": "https://polymarket.com/event/world-cup-winner/will-qatar-win-the-2026-fifa-world-cup",
          "side": "YES",
          "price": 0.0005,
          "depth_usd_at_price": 4305189,
          "last_trade_at": "2026-06-11T19:42:19.382575Z",
          "volume_24h_usd": 289363
        },
        {
          "platform": "polymarket",
          "market_id": "558946",
          "market_url": "https://polymarket.com/event/world-cup-winner/will-belgium-win-the-2026-fifa-world-cup-358",
          "side": "YES",
          "price": 0.0205,
          "depth_usd_at_price": 493894,
          "last_trade_at": "2026-06-11T19:39:33.02451Z",
          "volume_24h_usd": 4374040
        },
        {
          "platform": "polymarket",
          "market_id": "558958",
          "market_url": "https://polymarket.com/event/world-cup-winner/will-australia-win-the-2026-fifa-world-cup-816",
          "side": "YES",
          "price": 0.0015,
          "depth_usd_at_price": 4439134,
          "last_trade_at": "2026-06-11T19:38:31.740278Z",
          "volume_24h_usd": 2087264
        },
        {
          "platform": "polymarket",
          "market_id": "558972",
          "market_url": "https://polymarket.com/event/world-cup-winner/will-saudi-arabia-win-the-2026-fifa-world-cup",
          "side": "YES",
          "price": 0.0005,
          "depth_usd_at_price": 3244849,
          "last_trade_at": "2026-06-11T19:48:05.442638Z",
          "volume_24h_usd": 1241767
        },
        {
          "platform": "polymarket",
          "market_id": "558975",
          "market_url": "https://polymarket.com/event/world-cup-winner/will-austria-win-the-2026-fifa-world-cup",
          "side": "YES",
          "price": 0.0045,
          "depth_usd_at_price": 953986,
          "last_trade_at": "2026-06-11T19:37:37.627922Z",
          "volume_24h_usd": 2899822
        },
        {
          "platform": "polymarket",
          "market_id": "558976",
          "market_url": "https://polymarket.com/event/world-cup-winner/will-croatia-win-the-2026-fifa-world-cup",
          "side": "YES",
          "price": 0.0085,
          "depth_usd_at_price": 655819,
          "last_trade_at": "2026-06-11T19:42:43.358508Z",
          "volume_24h_usd": 2924357
        },
        {
          "platform": "polymarket",
          "market_id": "558968",
          "market_url": "https://polymarket.com/event/world-cup-winner/will-egypt-win-the-2026-fifa-world-cup",
          "side": "YES",
          "price": 0.0025,
          "depth_usd_at_price": 1650082,
          "last_trade_at": "2026-06-11T19:47:34.330408Z",
          "volume_24h_usd": 2237856
        },
        {
          "platform": "polymarket",
          "market_id": "558980",
          "market_url": "https://polymarket.com/event/world-cup-winner/will-sweden-win-the-2026-fifa-world-cup",
          "side": "YES",
          "price": 0.0035,
          "depth_usd_at_price": 2631740,
          "last_trade_at": "2026-06-11T19:38:38.441384Z",
          "volume_24h_usd": 3318802
        }
      ],
      "edge_gross_pct": 4.4,
      "edge_net_estimate_pct": -7.85,
      "max_executable_size_per_leg_usd": 137070,
      "edge_net_per_dollar": -0.0785,
      "weakest_link_summary": "Net edge negative after fees at any size — sum violation exists but Polymarket fees + spread on 48 legs consume it.",
      "confidence_flags": [
        "fee_tight"
      ],
      "persistence": {
        "first_seen_at": "2026-05-28T22:42:41.077Z",
        "scans_seen": 1323,
        "hours_persisted": 333.13,
        "gross_pct_history": [
          4.1,
          3.4,
          3.3,
          3.35,
          3.5,
          3.55,
          3.8,
          3.9,
          4,
          4.4
        ],
        "trend": "stable"
      }
    },
    {
      "id": "pass1-poly-sum-presidential-election-winner-2028-underpriced",
      "tier": 2,
      "type": "poly_sum_violation",
      "summary": "Polymarket negRisk: Presidential Election Winner 2028 — 36 legs sum to 0.927 (7.3pp underpriced; buy-all-YES)",
      "underlying": "OTHER",
      "resolution_date": "2028-11-07",
      "resolution_type": "quarterly",
      "legs": [
        {
          "platform": "polymarket",
          "market_id": "561263",
          "market_url": "https://polymarket.com/event/presidential-election-winner-2028/will-eric-trump-win-the-2028-us-presidential-election",
          "side": "YES",
          "price": 0.0065,
          "depth_usd_at_price": 449385,
          "last_trade_at": "2026-06-11T19:48:20.739897Z",
          "volume_24h_usd": 31100
        },
        {
          "platform": "polymarket",
          "market_id": "561229",
          "market_url": "https://polymarket.com/event/presidential-election-winner-2028/will-jd-vance-win-the-2028-us-presidential-election",
          "side": "YES",
          "price": 0.1495,
          "depth_usd_at_price": 164230,
          "last_trade_at": "2026-06-11T19:37:40.772721Z",
          "volume_24h_usd": 27180
        },
        {
          "platform": "polymarket",
          "market_id": "561250",
          "market_url": "https://polymarket.com/event/presidential-election-winner-2028/will-elon-musk-win-the-2028-us-presidential-election",
          "side": "YES",
          "price": 0.0095,
          "depth_usd_at_price": 396236,
          "last_trade_at": "2026-06-11T19:41:19.159851Z",
          "volume_24h_usd": 1220
        },
        {
          "platform": "polymarket",
          "market_id": "561230",
          "market_url": "https://polymarket.com/event/presidential-election-winner-2028/will-gavin-newsom-win-the-2028-us-presidential-election",
          "side": "YES",
          "price": 0.1485,
          "depth_usd_at_price": 87365,
          "last_trade_at": "2026-06-11T19:37:51.694073Z",
          "volume_24h_usd": 32082
        },
        {
          "platform": "polymarket",
          "market_id": "561232",
          "market_url": "https://polymarket.com/event/presidential-election-winner-2028/will-pete-buttigieg-win-the-2028-us-presidential-election",
          "side": "YES",
          "price": 0.024,
          "depth_usd_at_price": 119152,
          "last_trade_at": "2026-06-11T19:38:58.252195Z",
          "volume_24h_usd": 3120
        },
        {
          "platform": "polymarket",
          "market_id": "561247",
          "market_url": "https://polymarket.com/event/presidential-election-winner-2028/will-tim-walz-win-the-2028-us-presidential-election",
          "side": "YES",
          "price": 0.0065,
          "depth_usd_at_price": 474948,
          "last_trade_at": "2026-06-11T19:42:29.401485Z",
          "volume_24h_usd": 29570
        },
        {
          "platform": "polymarket",
          "market_id": "561261",
          "market_url": "https://polymarket.com/event/presidential-election-winner-2028/will-jon-ossoff-win-the-2028-us-presidential-election",
          "side": "YES",
          "price": 0.0435,
          "depth_usd_at_price": 80057,
          "last_trade_at": "2026-06-11T19:48:26.43022Z",
          "volume_24h_usd": 865
        },
        {
          "platform": "polymarket",
          "market_id": "561233",
          "market_url": "https://polymarket.com/event/presidential-election-winner-2028/will-josh-shapiro-win-the-2028-us-presidential-election",
          "side": "YES",
          "price": 0.0295,
          "depth_usd_at_price": 105146,
          "last_trade_at": "2026-06-11T19:38:58.466058Z",
          "volume_24h_usd": 6573
        },
        {
          "platform": "polymarket",
          "market_id": "561236",
          "market_url": "https://polymarket.com/event/presidential-election-winner-2028/will-gretchen-whitmer-win-the-2028-us-presidential-election",
          "side": "YES",
          "price": 0.0065,
          "depth_usd_at_price": 345342,
          "last_trade_at": "2026-06-11T19:38:49.390833Z",
          "volume_24h_usd": 25389
        },
        {
          "platform": "polymarket",
          "market_id": "561234",
          "market_url": "https://polymarket.com/event/presidential-election-winner-2028/will-marco-rubio-win-the-2028-us-presidential-election",
          "side": "YES",
          "price": 0.1475,
          "depth_usd_at_price": 78822,
          "last_trade_at": "2026-06-11T19:37:38.961566Z",
          "volume_24h_usd": 21418
        },
        {
          "platform": "polymarket",
          "market_id": "561231",
          "market_url": "https://polymarket.com/event/presidential-election-winner-2028/will-alexandria-ocasio-cortez-win-the-2028-us-presidential-election",
          "side": "YES",
          "price": 0.0525,
          "depth_usd_at_price": 103633,
          "last_trade_at": "2026-06-11T19:42:48.362351Z",
          "volume_24h_usd": 10838
        },
        {
          "platform": "polymarket",
          "market_id": "561235",
          "market_url": "https://polymarket.com/event/presidential-election-winner-2028/will-wes-moore-win-the-2028-us-presidential-election",
          "side": "YES",
          "price": 0.0075,
          "depth_usd_at_price": 269361,
          "last_trade_at": "2026-06-11T19:48:27.360585Z",
          "volume_24h_usd": 45472
        },
        {
          "platform": "polymarket",
          "market_id": "561246",
          "market_url": "https://polymarket.com/event/presidential-election-winner-2028/will-ron-desantis-win-the-2028-us-presidential-election",
          "side": "YES",
          "price": 0.0145,
          "depth_usd_at_price": 60620,
          "last_trade_at": "2026-06-11T19:37:34.226332Z",
          "volume_24h_usd": 1032
        },
        {
          "platform": "polymarket",
          "market_id": "561251",
          "market_url": "https://polymarket.com/event/presidential-election-winner-2028/will-lebron-james-win-the-2028-us-presidential-election",
          "side": "YES",
          "price": 0.0065,
          "depth_usd_at_price": 576155,
          "last_trade_at": "2026-06-11T19:41:59.437233Z",
          "volume_24h_usd": 30913
        },
        {
          "platform": "polymarket",
          "market_id": "561237",
          "market_url": "https://polymarket.com/event/presidential-election-winner-2028/will-andy-beshear-win-the-2028-us-presidential-election",
          "side": "YES",
          "price": 0.0165,
          "depth_usd_at_price": 119438,
          "last_trade_at": "2026-06-11T19:41:07.379799Z",
          "volume_24h_usd": 3408
        },
        {
          "platform": "polymarket",
          "market_id": "561238",
          "market_url": "https://polymarket.com/event/presidential-election-winner-2028/will-glenn-youngkin-win-the-2028-us-presidential-election",
          "side": "YES",
          "price": 0.0075,
          "depth_usd_at_price": 291303,
          "last_trade_at": "2026-06-11T19:38:21.905621Z",
          "volume_24h_usd": 17499
        },
        {
          "platform": "polymarket",
          "market_id": "561253",
          "market_url": "https://polymarket.com/event/presidential-election-winner-2028/will-tucker-carlson-win-the-2028-us-presidential-election",
          "side": "YES",
          "price": 0.0305,
          "depth_usd_at_price": 70293,
          "last_trade_at": "2026-06-11T19:37:35.153522Z",
          "volume_24h_usd": 14741
        },
        {
          "platform": "polymarket",
          "market_id": "561239",
          "market_url": "https://polymarket.com/event/presidential-election-winner-2028/will-kamala-harris-win-the-2028-us-presidential-election",
          "side": "YES",
          "price": 0.0505,
          "depth_usd_at_price": 86888,
          "last_trade_at": "2026-06-11T19:37:46.595702Z",
          "volume_24h_usd": 10083
        },
        {
          "platform": "polymarket",
          "market_id": "561255",
          "market_url": "https://polymarket.com/event/presidential-election-winner-2028/will-ivanka-trump-win-the-2028-us-presidential-election",
          "side": "YES",
          "price": 0.0075,
          "depth_usd_at_price": 146105,
          "last_trade_at": "2026-06-11T19:39:12.481565Z",
          "volume_24h_usd": 32918
        },
        {
          "platform": "polymarket",
          "market_id": "561240",
          "market_url": "https://polymarket.com/event/presidential-election-winner-2028/will-stephen-smith-win-the-2028-us-presidential-election",
          "side": "YES",
          "price": 0.0085,
          "depth_usd_at_price": 255122,
          "last_trade_at": "2026-06-11T19:37:39.019443Z",
          "volume_24h_usd": 21385
        },
        {
          "platform": "polymarket",
          "market_id": "561242",
          "market_url": "https://polymarket.com/event/presidential-election-winner-2028/will-tulsi-gabbard-win-the-2028-us-presidential-election",
          "side": "YES",
          "price": 0.0075,
          "depth_usd_at_price": 341342,
          "last_trade_at": "2026-06-11T19:42:34.953831Z",
          "volume_24h_usd": 22725
        },
        {
          "platform": "polymarket",
          "market_id": "561264",
          "market_url": "https://polymarket.com/event/presidential-election-winner-2028/will-pete-hegseth-win-the-2028-us-presidential-election",
          "side": "YES",
          "price": 0.0065,
          "depth_usd_at_price": 451727,
          "last_trade_at": "2026-06-11T19:48:24.800537Z",
          "volume_24h_usd": 23488
        },
        {
          "platform": "polymarket",
          "market_id": "561241",
          "market_url": "https://polymarket.com/event/presidential-election-winner-2028/will-jb-pritzker-win-the-2028-us-presidential-election",
          "side": "YES",
          "price": 0.0105,
          "depth_usd_at_price": 139036,
          "last_trade_at": "2026-06-11T19:40:01.572889Z",
          "volume_24h_usd": 5747
        },
        {
          "platform": "polymarket",
          "market_id": "561243",
          "market_url": "https://polymarket.com/event/presidential-election-winner-2028/will-donald-trump-win-the-2028-us-presidential-election",
          "side": "YES",
          "price": 0.0145,
          "depth_usd_at_price": 179288,
          "last_trade_at": "2026-06-11T19:42:49.355342Z",
          "volume_24h_usd": 10334
        },
        {
          "platform": "polymarket",
          "market_id": "561258",
          "market_url": "https://polymarket.com/event/presidential-election-winner-2028/will-jamie-dimon-win-the-2028-us-presidential-election",
          "side": "YES",
          "price": 0.0105,
          "depth_usd_at_price": 200765,
          "last_trade_at": "2026-06-11T19:39:58.308823Z",
          "volume_24h_usd": 3220
        },
        {
          "platform": "polymarket",
          "market_id": "561244",
          "market_url": "https://polymarket.com/event/presidential-election-winner-2028/will-donald-trump-jr-win-the-2028-us-presidential-election",
          "side": "YES",
          "price": 0.0115,
          "depth_usd_at_price": 236768,
          "last_trade_at": "2026-06-11T19:38:55.86485Z",
          "volume_24h_usd": 18946
        },
        {
          "platform": "polymarket",
          "market_id": "561245",
          "market_url": "https://polymarket.com/event/presidential-election-winner-2028/will-nikki-haley-win-the-2028-us-presidential-election",
          "side": "YES",
          "price": 0.0065,
          "depth_usd_at_price": 443038,
          "last_trade_at": "2026-06-11T19:47:11.411221Z",
          "volume_24h_usd": 28891
        },
        {
          "platform": "polymarket",
          "market_id": "561248",
          "market_url": "https://polymarket.com/event/presidential-election-winner-2028/will-vivek-ramaswamy-win-the-2028-us-presidential-election",
          "side": "YES",
          "price": 0.0075,
          "depth_usd_at_price": 236027,
          "last_trade_at": "2026-06-11T19:39:00.138258Z",
          "volume_24h_usd": 22153
        },
        {
          "platform": "polymarket",
          "market_id": "561249",
          "market_url": "https://polymarket.com/event/presidential-election-winner-2028/will-greg-abbott-win-the-2028-us-presidential-election",
          "side": "YES",
          "price": 0.0085,
          "depth_usd_at_price": 540732,
          "last_trade_at": "2026-06-11T19:40:58.07304Z",
          "volume_24h_usd": 36814
        },
        {
          "platform": "polymarket",
          "market_id": "561252",
          "market_url": "https://polymarket.com/event/presidential-election-winner-2028/will-dwayne-the-rock-johnson-win-the-2028-us-presidential-election",
          "side": "YES",
          "price": 0.0165,
          "depth_usd_at_price": 51927,
          "last_trade_at": "2026-06-11T19:37:42.77998Z",
          "volume_24h_usd": 6959
        },
        {
          "platform": "polymarket",
          "market_id": "561254",
          "market_url": "https://polymarket.com/event/presidential-election-winner-2028/will-kim-kardashian-win-the-2028-us-presidential-election",
          "side": "YES",
          "price": 0.0065,
          "depth_usd_at_price": 448759,
          "last_trade_at": "2026-06-11T19:41:26.160102Z",
          "volume_24h_usd": 36059
        },
        {
          "platform": "polymarket",
          "market_id": "561256",
          "market_url": "https://polymarket.com/event/presidential-election-winner-2028/will-zohran-mamdani-win-the-2028-us-presidential-election",
          "side": "YES",
          "price": 0.0075,
          "depth_usd_at_price": 421043,
          "last_trade_at": "2026-06-11T19:42:43.721717Z",
          "volume_24h_usd": 52488
        },
        {
          "platform": "polymarket",
          "market_id": "561257",
          "market_url": "https://polymarket.com/event/presidential-election-winner-2028/will-michelle-obama-win-the-2028-us-presidential-election",
          "side": "YES",
          "price": 0.0075,
          "depth_usd_at_price": 371513,
          "last_trade_at": "2026-06-11T19:39:43.929178Z",
          "volume_24h_usd": 36284
        },
        {
          "platform": "polymarket",
          "market_id": "561259",
          "market_url": "https://polymarket.com/event/presidential-election-winner-2028/will-ro-khanna-win-the-2028-us-presidential-election",
          "side": "YES",
          "price": 0.0105,
          "depth_usd_at_price": 39481,
          "last_trade_at": "2026-06-11T19:47:29.363297Z",
          "volume_24h_usd": 445326
        },
        {
          "platform": "polymarket",
          "market_id": "561260",
          "market_url": "https://polymarket.com/event/presidential-election-winner-2028/will-thomas-massie-win-the-2028-us-presidential-election",
          "side": "YES",
          "price": 0.0135,
          "depth_usd_at_price": 203519,
          "last_trade_at": "2026-06-11T19:38:55.821421Z",
          "volume_24h_usd": 4568
        },
        {
          "platform": "polymarket",
          "market_id": "561262",
          "market_url": "https://polymarket.com/event/presidential-election-winner-2028/will-james-talarico-win-the-2028-us-presidential-election",
          "side": "YES",
          "price": 0.0085,
          "depth_usd_at_price": 153726,
          "last_trade_at": "2026-06-11T19:39:59.464767Z",
          "volume_24h_usd": 19009
        }
      ],
      "edge_gross_pct": 7.25,
      "edge_net_estimate_pct": -21.18,
      "max_executable_size_per_leg_usd": 39481,
      "edge_net_per_dollar": -0.2118,
      "weakest_link_summary": "Net edge negative after fees at any size — sum violation exists but Polymarket fees + spread on 36 legs consume it.",
      "confidence_flags": [
        "fee_tight",
        "resolution_mismatch",
        "low_volume"
      ],
      "persistence": {
        "first_seen_at": "2026-05-28T19:56:52.494Z",
        "scans_seen": 1316,
        "hours_persisted": 335.89,
        "gross_pct_history": [
          7.35,
          7.35,
          7.25,
          6.8,
          6.15,
          6.15,
          6.15,
          7.3,
          7.25,
          7.25
        ],
        "trend": "stable"
      }
    },
    {
      "id": "pass3-kalshi-mono-SOL-above-2026-06-18-daily-KXSOLD-26JUN1117-T62.9999-KXSOLD-26JUN1117-T63.9999",
      "tier": 3,
      "type": "kalshi_monotonicity",
      "summary": "Kalshi SOL above-$63 priced 0.950 but above-$64 priced 0.970 — strike monotonicity violation (2026-06-18 · daily)",
      "underlying": "SOL",
      "resolution_date": "2026-06-18",
      "resolution_type": "daily",
      "legs": [
        {
          "platform": "kalshi",
          "market_id": "KXSOLD-26JUN1117-T62.9999",
          "market_url": "https://kalshi.com/markets/KXSOLD-26JUN1117/KXSOLD-26JUN1117-T62.9999",
          "side": "YES",
          "price": 0.95,
          "depth_usd_at_price": 898,
          "last_trade_at": "2026-06-10T20:00:00.706328Z",
          "volume_24h_usd": 2434
        },
        {
          "platform": "kalshi",
          "market_id": "KXSOLD-26JUN1117-T63.9999",
          "market_url": "https://kalshi.com/markets/KXSOLD-26JUN1117/KXSOLD-26JUN1117-T63.9999",
          "side": "NO",
          "price": 0.03,
          "depth_usd_at_price": 653,
          "last_trade_at": "2026-06-10T20:00:00.706328Z",
          "volume_24h_usd": 2769
        }
      ],
      "edge_gross_pct": 2,
      "edge_net_estimate_pct": -0.69,
      "max_executable_size_per_leg_usd": 653,
      "edge_net_per_dollar": -0.0069,
      "weakest_link_summary": "Net edge negative after Kalshi 0.07·C·P·(1−P) fees and spread on both legs.",
      "confidence_flags": [
        "stale_price",
        "fee_tight"
      ],
      "persistence": {
        "first_seen_at": "2026-06-11T19:50:15.091Z",
        "scans_seen": 1,
        "hours_persisted": 0,
        "gross_pct_history": [
          2
        ],
        "trend": "new"
      }
    },
    {
      "id": "pass1-poly-sum-harvey-weinstein-prison-time-underpriced",
      "tier": 3,
      "type": "poly_sum_violation",
      "summary": "Polymarket negRisk: Harvey Weinstein prison time? — 6 legs sum to 0.965 (3.5pp underpriced; buy-all-YES)",
      "underlying": "OTHER",
      "resolution_date": "2025-12-31",
      "resolution_type": "hourly",
      "legs": [
        {
          "platform": "polymarket",
          "market_id": "544092",
          "market_url": "https://polymarket.com/event/harvey-weinstein-prison-time/will-harvey-weinstein-be-sentenced-to-no-prison-time",
          "side": "YES",
          "price": 0.8205,
          "depth_usd_at_price": 494,
          "last_trade_at": "2026-06-11T19:38:48.411789Z",
          "volume_24h_usd": 74
        },
        {
          "platform": "polymarket",
          "market_id": "544093",
          "market_url": "https://polymarket.com/event/harvey-weinstein-prison-time/will-harvey-weinstein-be-sentenced-to-less-than-5-years-in-prison",
          "side": "YES",
          "price": 0.0285,
          "depth_usd_at_price": 1130,
          "last_trade_at": "2026-06-11T19:38:14.496687Z",
          "volume_24h_usd": 213
        },
        {
          "platform": "polymarket",
          "market_id": "544094",
          "market_url": "https://polymarket.com/event/harvey-weinstein-prison-time/will-harvey-weinstein-be-sentenced-to-between-5-and-10-years-in-prison",
          "side": "YES",
          "price": 0.0235,
          "depth_usd_at_price": 982,
          "last_trade_at": "2026-06-11T19:42:05.332222Z",
          "volume_24h_usd": 207
        },
        {
          "platform": "polymarket",
          "market_id": "544095",
          "market_url": "https://polymarket.com/event/harvey-weinstein-prison-time/will-harvey-weinstein-be-sentenced-to-between-10-and-20-years-in-prison",
          "side": "YES",
          "price": 0.022,
          "depth_usd_at_price": 1059,
          "last_trade_at": "2026-06-11T19:39:08.482125Z",
          "volume_24h_usd": 18
        },
        {
          "platform": "polymarket",
          "market_id": "544096",
          "market_url": "https://polymarket.com/event/harvey-weinstein-prison-time/will-harvey-weinstein-be-sentenced-to-between-20-and-30-years-in-prison",
          "side": "YES",
          "price": 0.0645,
          "depth_usd_at_price": 1180,
          "last_trade_at": "2026-06-11T19:48:40.953729Z",
          "volume_24h_usd": 318
        },
        {
          "platform": "polymarket",
          "market_id": "544097",
          "market_url": "https://polymarket.com/event/harvey-weinstein-prison-time/will-harvey-weinstein-be-sentenced-to-more-than-30-years-in-prison",
          "side": "YES",
          "price": 0.0065,
          "depth_usd_at_price": 1087,
          "last_trade_at": "2026-06-11T19:47:01.292321Z",
          "volume_24h_usd": 309
        }
      ],
      "edge_gross_pct": 3.45,
      "edge_net_estimate_pct": -0.87,
      "max_executable_size_per_leg_usd": 494,
      "edge_net_per_dollar": -0.0087,
      "weakest_link_summary": "Net edge negative after fees at any size — sum violation exists but Polymarket fees + spread on 6 legs consume it.",
      "confidence_flags": [
        "stale_price",
        "fee_tight",
        "low_volume"
      ],
      "persistence": {
        "first_seen_at": "2026-05-28T23:12:41.515Z",
        "scans_seen": 516,
        "hours_persisted": 332.63,
        "gross_pct_history": [
          5.5,
          3.45,
          3.45,
          3.4,
          3.45,
          3.45,
          3.45,
          3.45,
          3.45,
          3.45
        ],
        "trend": "stable"
      }
    },
    {
      "id": "pass1-poly-sum-michigan-democratic-senate-primary-winner-underpriced",
      "tier": 3,
      "type": "poly_sum_violation",
      "summary": "Polymarket negRisk: Michigan Democratic Senate Primary Winner — 9 legs sum to 0.980 (1.9pp underpriced; buy-all-YES)",
      "underlying": "OTHER",
      "resolution_date": "2026-08-04",
      "resolution_type": "monthly",
      "legs": [
        {
          "platform": "polymarket",
          "market_id": "599303",
          "market_url": "https://polymarket.com/event/michigan-democratic-senate-primary-winner/will-mallory-mcmorrow-win-the-2026-michigan-democratic-primary",
          "side": "YES",
          "price": 0.065,
          "depth_usd_at_price": 4840,
          "last_trade_at": "2026-06-11T19:42:44.92822Z",
          "volume_24h_usd": 175
        },
        {
          "platform": "polymarket",
          "market_id": "599304",
          "market_url": "https://polymarket.com/event/michigan-democratic-senate-primary-winner/will-haley-stevens-win-the-2026-michigan-democratic-primary",
          "side": "YES",
          "price": 0.2325,
          "depth_usd_at_price": 3984,
          "last_trade_at": null,
          "volume_24h_usd": 0
        },
        {
          "platform": "polymarket",
          "market_id": "599305",
          "market_url": "https://polymarket.com/event/michigan-democratic-senate-primary-winner/will-abdul-el-sayed-win-the-2026-michigan-democratic-primary",
          "side": "YES",
          "price": 0.675,
          "depth_usd_at_price": 2740,
          "last_trade_at": "2026-06-11T19:39:29.074515Z",
          "volume_24h_usd": 105
        },
        {
          "platform": "polymarket",
          "market_id": "599306",
          "market_url": "https://polymarket.com/event/michigan-democratic-senate-primary-winner/will-dana-nessel-win-the-2026-michigan-democratic-primary",
          "side": "YES",
          "price": 0.0005,
          "depth_usd_at_price": 3235,
          "last_trade_at": null,
          "volume_24h_usd": 0
        },
        {
          "platform": "polymarket",
          "market_id": "599307",
          "market_url": "https://polymarket.com/event/michigan-democratic-senate-primary-winner/will-rashida-tlaib-win-the-2026-michigan-democratic-primary",
          "side": "YES",
          "price": 0.0015,
          "depth_usd_at_price": 3817,
          "last_trade_at": null,
          "volume_24h_usd": 0
        },
        {
          "platform": "polymarket",
          "market_id": "599308",
          "market_url": "https://polymarket.com/event/michigan-democratic-senate-primary-winner/will-sarah-anthony-win-the-2026-michigan-democratic-primary",
          "side": "YES",
          "price": 0.0015,
          "depth_usd_at_price": 3485,
          "last_trade_at": null,
          "volume_24h_usd": 0
        },
        {
          "platform": "polymarket",
          "market_id": "599309",
          "market_url": "https://polymarket.com/event/michigan-democratic-senate-primary-winner/will-kristen-mcdonald-rivet-win-the-2026-michigan-democratic-primary",
          "side": "YES",
          "price": 0.0015,
          "depth_usd_at_price": 2505,
          "last_trade_at": "2026-06-11T19:38:37.827762Z",
          "volume_24h_usd": 2734
        },
        {
          "platform": "polymarket",
          "market_id": "599310",
          "market_url": "https://polymarket.com/event/michigan-democratic-senate-primary-winner/will-andy-levin-win-the-2026-michigan-democratic-primary",
          "side": "YES",
          "price": 0.0015,
          "depth_usd_at_price": 3358,
          "last_trade_at": null,
          "volume_24h_usd": 0
        },
        {
          "platform": "polymarket",
          "market_id": "599311",
          "market_url": "https://polymarket.com/event/michigan-democratic-senate-primary-winner/will-matt-sahr-win-the-2026-michigan-democratic-primary",
          "side": "YES",
          "price": 0.0015,
          "depth_usd_at_price": 3933,
          "last_trade_at": "2026-06-11T19:42:14.972075Z",
          "volume_24h_usd": 542
        }
      ],
      "edge_gross_pct": 1.95,
      "edge_net_estimate_pct": -5.36,
      "max_executable_size_per_leg_usd": 2505,
      "edge_net_per_dollar": -0.0536,
      "weakest_link_summary": "Net edge negative after fees at any size — sum violation exists but Polymarket fees + spread on 9 legs consume it.",
      "confidence_flags": [
        "stale_price",
        "low_volume"
      ],
      "persistence": {
        "first_seen_at": "2026-06-01T12:41:47.441Z",
        "scans_seen": 257,
        "hours_persisted": 247.14,
        "gross_pct_history": [
          1.95,
          1.95,
          2.95,
          2.9,
          1.95,
          1.95,
          1.95,
          1.95,
          1.95,
          1.95
        ],
        "trend": "stable"
      }
    },
    {
      "id": "pass4-curated-btc-year-end-2026-BTC-above-150000-poly573656-kalshiKXBTCMAXY-26DEC31-149999.99",
      "tier": 3,
      "type": "cross_platform",
      "summary": "[curated:btc-year-end-2026] BTC above-$150,000 — Polymarket YES 0.070 vs Kalshi YES 0.045 (Poly higher by 2.5pp)",
      "underlying": "BTC",
      "resolution_date": "2027-01-01",
      "resolution_type": "quarterly",
      "legs": [
        {
          "platform": "kalshi",
          "market_id": "KXBTCMAXY-26DEC31-149999.99",
          "market_url": "https://kalshi.com/markets/KXBTCMAXY-26DEC31/KXBTCMAXY-26DEC31-149999.99",
          "side": "YES",
          "price": 0.045,
          "depth_usd_at_price": 197,
          "last_trade_at": "2026-04-09T10:34:58.083531Z",
          "volume_24h_usd": 390
        },
        {
          "platform": "polymarket",
          "market_id": "573656",
          "market_url": "https://polymarket.com/event/when-will-bitcoin-hit-150k/will-bitcoin-hit-150k-by-december-31-2026",
          "side": "NO",
          "price": 0.93,
          "depth_usd_at_price": 22941,
          "last_trade_at": "2026-06-11T19:42:55.286493Z",
          "volume_24h_usd": 8425
        }
      ],
      "edge_gross_pct": 2.5,
      "edge_net_estimate_pct": -5.44,
      "max_executable_size_per_leg_usd": 197,
      "edge_net_per_dollar": -0.0544,
      "weakest_link_summary": "Net edge negative after fees — Poly taker + Kalshi 0.07·C·P·(1−P) + spread + bridge consume the spread.",
      "confidence_flags": [
        "stale_price",
        "depth_limited",
        "low_volume",
        "curated_pair"
      ],
      "curated_pair_id": "btc-year-end-2026",
      "persistence": {
        "first_seen_at": "2026-06-02T16:49:35.290Z",
        "scans_seen": 311,
        "hours_persisted": 219.01,
        "gross_pct_history": [
          3,
          3,
          3,
          3,
          2.5,
          2.5,
          2.5,
          2.5,
          2.5,
          2.5
        ],
        "trend": "stable"
      }
    },
    {
      "id": "pass1-poly-sum-balance-of-power-2026-midterms-underpriced",
      "tier": 3,
      "type": "poly_sum_violation",
      "summary": "Polymarket negRisk: Balance of Power: 2026 Midterms — 5 legs sum to 0.983 (1.7pp underpriced; buy-all-YES)",
      "underlying": "OTHER",
      "resolution_date": "2026-11-03",
      "resolution_type": "quarterly",
      "legs": [
        {
          "platform": "polymarket",
          "market_id": "562828",
          "market_url": "https://polymarket.com/event/balance-of-power-2026-midterms/2026-balance-of-power-d-senate-d-house-949",
          "side": "YES",
          "price": 0.435,
          "depth_usd_at_price": 35996,
          "last_trade_at": "2026-06-11T19:37:06.457739Z",
          "volume_24h_usd": 3959
        },
        {
          "platform": "polymarket",
          "market_id": "562829",
          "market_url": "https://polymarket.com/event/balance-of-power-2026-midterms/2026-balance-of-power-d-senate-r-house-692",
          "side": "YES",
          "price": 0.0195,
          "depth_usd_at_price": 43174,
          "last_trade_at": "2026-06-11T19:42:52.787564Z",
          "volume_24h_usd": 1182
        },
        {
          "platform": "polymarket",
          "market_id": "562830",
          "market_url": "https://polymarket.com/event/balance-of-power-2026-midterms/2026-balance-of-power-r-senate-d-house-444",
          "side": "YES",
          "price": 0.345,
          "depth_usd_at_price": 32802,
          "last_trade_at": "2026-06-11T19:37:01.080814Z",
          "volume_24h_usd": 9146
        },
        {
          "platform": "polymarket",
          "market_id": "562831",
          "market_url": "https://polymarket.com/event/balance-of-power-2026-midterms/2026-balance-of-power-r-senate-r-house-537",
          "side": "YES",
          "price": 0.175,
          "depth_usd_at_price": 53918,
          "last_trade_at": "2026-06-11T19:47:05.769404Z",
          "volume_24h_usd": 441
        },
        {
          "platform": "polymarket",
          "market_id": "562832",
          "market_url": "https://polymarket.com/event/balance-of-power-2026-midterms/2026-balance-of-power-other-131",
          "side": "YES",
          "price": 0.0085,
          "depth_usd_at_price": 29999,
          "last_trade_at": "2026-06-11T19:41:57.500657Z",
          "volume_24h_usd": 4585
        }
      ],
      "edge_gross_pct": 1.7,
      "edge_net_estimate_pct": -8.62,
      "max_executable_size_per_leg_usd": 29999,
      "edge_net_per_dollar": -0.0862,
      "weakest_link_summary": "Net edge negative after fees at any size — sum violation exists but Polymarket fees + spread on 5 legs consume it.",
      "confidence_flags": [
        "low_volume"
      ],
      "persistence": {
        "first_seen_at": "2026-06-11T05:00:18.306Z",
        "scans_seen": 60,
        "hours_persisted": 14.83,
        "gross_pct_history": [
          1.7,
          1.7,
          1.7,
          1.7,
          1.7,
          1.7,
          1.7,
          1.7,
          1.7,
          1.7
        ],
        "trend": "stable"
      }
    },
    {
      "id": "pass1-poly-sum-democratic-presidential-nominee-2028-underpriced",
      "tier": 3,
      "type": "poly_sum_violation",
      "summary": "Polymarket negRisk: Democratic Presidential Nominee 2028 — 45 legs sum to 0.969 (3.0pp underpriced; buy-all-YES)",
      "underlying": "OTHER",
      "resolution_date": "2028-11-07",
      "resolution_type": "quarterly",
      "legs": [
        {
          "platform": "polymarket",
          "market_id": "559657",
          "market_url": "https://polymarket.com/event/democratic-presidential-nominee-2028/will-stephen-a-smith-win-the-2028-democratic-presidential-nomination-914",
          "side": "YES",
          "price": 0.0105,
          "depth_usd_at_price": 242679,
          "last_trade_at": "2026-06-11T19:42:00.258235Z",
          "volume_24h_usd": 892
        },
        {
          "platform": "polymarket",
          "market_id": "559659",
          "market_url": "https://polymarket.com/event/democratic-presidential-nominee-2028/will-gretchen-whitmer-win-the-2028-democratic-presidential-nomination-676",
          "side": "YES",
          "price": 0.0085,
          "depth_usd_at_price": 165707,
          "last_trade_at": "2026-06-11T19:37:45.24008Z",
          "volume_24h_usd": 32060
        },
        {
          "platform": "polymarket",
          "market_id": "559687",
          "market_url": "https://polymarket.com/event/democratic-presidential-nominee-2028/will-oprah-winfrey-win-the-2028-democratic-presidential-nomination",
          "side": "YES",
          "price": 0.0075,
          "depth_usd_at_price": 657703,
          "last_trade_at": "2026-06-11T19:37:31.414087Z",
          "volume_24h_usd": 26073
        },
        {
          "platform": "polymarket",
          "market_id": "559660",
          "market_url": "https://polymarket.com/event/democratic-presidential-nominee-2028/will-andy-beshear-win-the-2028-democratic-presidential-nomination-832",
          "side": "YES",
          "price": 0.0275,
          "depth_usd_at_price": 104586,
          "last_trade_at": "2026-06-11T19:42:33.756823Z",
          "volume_24h_usd": 2147
        },
        {
          "platform": "polymarket",
          "market_id": "559695",
          "market_url": "https://polymarket.com/event/democratic-presidential-nominee-2028/will-james-talarico-win-the-2028-democratic-presidential-nomination",
          "side": "YES",
          "price": 0.0205,
          "depth_usd_at_price": 66549,
          "last_trade_at": "2026-06-11T19:38:13.810831Z",
          "volume_24h_usd": 71818
        },
        {
          "platform": "polymarket",
          "market_id": "559654",
          "market_url": "https://polymarket.com/event/democratic-presidential-nominee-2028/will-pete-buttigieg-win-the-2028-democratic-presidential-nomination-687",
          "side": "YES",
          "price": 0.0435,
          "depth_usd_at_price": 95498,
          "last_trade_at": "2026-06-11T19:42:50.589703Z",
          "volume_24h_usd": 3048
        },
        {
          "platform": "polymarket",
          "market_id": "559661",
          "market_url": "https://polymarket.com/event/democratic-presidential-nominee-2028/will-jon-ossoff-win-the-2028-democratic-presidential-nomination-885",
          "side": "YES",
          "price": 0.0745,
          "depth_usd_at_price": 54262,
          "last_trade_at": "2026-06-11T19:39:41.383248Z",
          "volume_24h_usd": 7787
        },
        {
          "platform": "polymarket",
          "market_id": "559670",
          "market_url": "https://polymarket.com/event/democratic-presidential-nominee-2028/will-gina-raimondo-win-the-2028-democratic-presidential-nomination-676",
          "side": "YES",
          "price": 0.0075,
          "depth_usd_at_price": 592942,
          "last_trade_at": "2026-06-11T19:47:06.399596Z",
          "volume_24h_usd": 21033
        },
        {
          "platform": "polymarket",
          "market_id": "559664",
          "market_url": "https://polymarket.com/event/democratic-presidential-nominee-2028/will-raphael-warnock-win-the-2028-democratic-presidential-nomination-914",
          "side": "YES",
          "price": 0.0075,
          "depth_usd_at_price": 479421,
          "last_trade_at": "2026-06-11T19:37:27.303276Z",
          "volume_24h_usd": 21128
        },
        {
          "platform": "polymarket",
          "market_id": "559676",
          "market_url": "https://polymarket.com/event/democratic-presidential-nominee-2028/will-barack-obama-win-the-2028-democratic-presidential-nomination-265",
          "side": "YES",
          "price": 0.0075,
          "depth_usd_at_price": 557180,
          "last_trade_at": "2026-06-11T19:48:27.957323Z",
          "volume_24h_usd": 33204
        },
        {
          "platform": "polymarket",
          "market_id": "559683",
          "market_url": "https://polymarket.com/event/democratic-presidential-nominee-2028/will-george-clooney-win-the-2028-democratic-presidential-nomination",
          "side": "YES",
          "price": 0.0065,
          "depth_usd_at_price": 636322,
          "last_trade_at": "2026-06-11T19:48:19.880445Z",
          "volume_24h_usd": 25623
        },
        {
          "platform": "polymarket",
          "market_id": "559665",
          "market_url": "https://polymarket.com/event/democratic-presidential-nominee-2028/will-corey-booker-win-the-2028-democratic-presidential-nomination-125",
          "side": "YES",
          "price": 0.0095,
          "depth_usd_at_price": 480214,
          "last_trade_at": "2026-06-11T19:38:57.624248Z",
          "volume_24h_usd": 1768
        },
        {
          "platform": "polymarket",
          "market_id": "559675",
          "market_url": "https://polymarket.com/event/democratic-presidential-nominee-2028/will-jon-stewart-win-the-2028-democratic-presidential-nomination-518",
          "side": "YES",
          "price": 0.0165,
          "depth_usd_at_price": 279093,
          "last_trade_at": "2026-06-11T19:39:43.32882Z",
          "volume_24h_usd": 4676
        },
        {
          "platform": "polymarket",
          "market_id": "559666",
          "market_url": "https://polymarket.com/event/democratic-presidential-nominee-2028/will-tim-walz-win-the-2028-democratic-presidential-nomination-475",
          "side": "YES",
          "price": 0.0065,
          "depth_usd_at_price": 607937,
          "last_trade_at": "2026-06-11T19:48:36.266424Z",
          "volume_24h_usd": 23064
        },
        {
          "platform": "polymarket",
          "market_id": "559679",
          "market_url": "https://polymarket.com/event/democratic-presidential-nominee-2028/will-bernie-sanders-win-the-2028-democratic-presidential-nomination-879",
          "side": "YES",
          "price": 0.0075,
          "depth_usd_at_price": 368628,
          "last_trade_at": "2026-06-11T19:40:09.625576Z",
          "volume_24h_usd": 13098
        },
        {
          "platform": "polymarket",
          "market_id": "559668",
          "market_url": "https://polymarket.com/event/democratic-presidential-nominee-2028/will-mark-kelly-win-the-2028-democratic-presidential-nomination-479",
          "side": "YES",
          "price": 0.0175,
          "depth_usd_at_price": 128480,
          "last_trade_at": "2026-06-11T19:37:30.358852Z",
          "volume_24h_usd": 11160
        },
        {
          "platform": "polymarket",
          "market_id": "559678",
          "market_url": "https://polymarket.com/event/democratic-presidential-nominee-2028/will-liz-cheney-win-the-2028-democratic-presidential-nomination-551",
          "side": "YES",
          "price": 0.0075,
          "depth_usd_at_price": 628715,
          "last_trade_at": "2026-06-11T19:39:45.59996Z",
          "volume_24h_usd": 22787
        },
        {
          "platform": "polymarket",
          "market_id": "559689",
          "market_url": "https://polymarket.com/event/democratic-presidential-nominee-2028/will-beto-orourke-win-the-2028-democratic-presidential-nomination",
          "side": "YES",
          "price": 0.0065,
          "depth_usd_at_price": 600389,
          "last_trade_at": "2026-06-11T19:47:27.75473Z",
          "volume_24h_usd": 25828
        },
        {
          "platform": "polymarket",
          "market_id": "559667",
          "market_url": "https://polymarket.com/event/democratic-presidential-nominee-2028/will-michelle-obama-win-the-2028-democratic-presidential-nomination-777",
          "side": "YES",
          "price": 0.0135,
          "depth_usd_at_price": 517008,
          "last_trade_at": "2026-06-11T19:47:15.1791Z",
          "volume_24h_usd": 37046
        },
        {
          "platform": "polymarket",
          "market_id": "559671",
          "market_url": "https://polymarket.com/event/democratic-presidential-nominee-2028/will-zohran-mamdani-win-the-2028-democratic-presidential-nomination-445",
          "side": "YES",
          "price": 0.0075,
          "depth_usd_at_price": 610256,
          "last_trade_at": "2026-06-11T19:39:26.05491Z",
          "volume_24h_usd": 24268
        },
        {
          "platform": "polymarket",
          "market_id": "559688",
          "market_url": "https://polymarket.com/event/democratic-presidential-nominee-2028/will-andrew-yang-win-the-2028-democratic-presidential-nomination",
          "side": "YES",
          "price": 0.0065,
          "depth_usd_at_price": 611506,
          "last_trade_at": "2026-06-11T19:47:03.853108Z",
          "volume_24h_usd": 29846
        },
        {
          "platform": "polymarket",
          "market_id": "559653",
          "market_url": "https://polymarket.com/event/democratic-presidential-nominee-2028/will-alexandria-ocasio-cortez-win-the-2028-democratic-presidential-nomination-653",
          "side": "YES",
          "price": 0.0885,
          "depth_usd_at_price": 66651,
          "last_trade_at": "2026-06-11T19:38:54.556619Z",
          "volume_24h_usd": 11408
        },
        {
          "platform": "polymarket",
          "market_id": "559669",
          "market_url": "https://polymarket.com/event/democratic-presidential-nominee-2028/will-rahm-emanuel-win-the-2028-democratic-presidential-nomination-299",
          "side": "YES",
          "price": 0.0175,
          "depth_usd_at_price": 194185,
          "last_trade_at": "2026-06-11T19:42:48.816059Z",
          "volume_24h_usd": 55139
        },
        {
          "platform": "polymarket",
          "market_id": "559673",
          "market_url": "https://polymarket.com/event/democratic-presidential-nominee-2028/will-john-fetterman-win-the-2028-democratic-presidential-nomination-941",
          "side": "YES",
          "price": 0.0085,
          "depth_usd_at_price": 383872,
          "last_trade_at": "2026-06-11T19:39:44.501177Z",
          "volume_24h_usd": 16199
        },
        {
          "platform": "polymarket",
          "market_id": "559690",
          "market_url": "https://polymarket.com/event/democratic-presidential-nominee-2028/will-kim-kardashian-win-the-2028-democratic-presidential-nomination",
          "side": "YES",
          "price": 0.0065,
          "depth_usd_at_price": 785427,
          "last_trade_at": "2026-06-11T19:38:14.669175Z",
          "volume_24h_usd": 22389
        },
        {
          "platform": "polymarket",
          "market_id": "559693",
          "market_url": "https://polymarket.com/event/democratic-presidential-nominee-2028/will-ruben-gallego-win-the-2028-democratic-presidential-nomination",
          "side": "YES",
          "price": 0.0075,
          "depth_usd_at_price": 264537,
          "last_trade_at": "2026-06-11T19:47:29.614031Z",
          "volume_24h_usd": 21568
        },
        {
          "platform": "polymarket",
          "market_id": "559674",
          "market_url": "https://polymarket.com/event/democratic-presidential-nominee-2028/will-jared-polis-win-the-2028-democratic-presidential-nomination-837",
          "side": "YES",
          "price": 0.0075,
          "depth_usd_at_price": 197324,
          "last_trade_at": "2026-06-11T19:42:43.242331Z",
          "volume_24h_usd": 22622
        },
        {
          "platform": "polymarket",
          "market_id": "559662",
          "market_url": "https://polymarket.com/event/democratic-presidential-nominee-2028/will-mark-cuban-win-the-2028-democratic-presidential-nomination-329",
          "side": "YES",
          "price": 0.0095,
          "depth_usd_at_price": 512972,
          "last_trade_at": "2026-06-11T19:47:08.955225Z",
          "volume_24h_usd": 6395
        },
        {
          "platform": "polymarket",
          "market_id": "559680",
          "market_url": "https://polymarket.com/event/democratic-presidential-nominee-2028/will-phil-murphy-win-the-2028-democratic-presidential-nomination-611",
          "side": "YES",
          "price": 0.0065,
          "depth_usd_at_price": 643248,
          "last_trade_at": "2026-06-11T19:42:49.098181Z",
          "volume_24h_usd": 31219
        },
        {
          "platform": "polymarket",
          "market_id": "559656",
          "market_url": "https://polymarket.com/event/democratic-presidential-nominee-2028/will-wes-moore-win-the-2028-democratic-presidential-nomination-714",
          "side": "YES",
          "price": 0.0135,
          "depth_usd_at_price": 126995,
          "last_trade_at": "2026-06-11T19:48:42.461324Z",
          "volume_24h_usd": 3963
        },
        {
          "platform": "polymarket",
          "market_id": "559663",
          "market_url": "https://polymarket.com/event/democratic-presidential-nominee-2028/will-jb-pritzker-win-the-2028-democratic-presidential-nomination-288",
          "side": "YES",
          "price": 0.0165,
          "depth_usd_at_price": 113461,
          "last_trade_at": "2026-06-11T19:42:45.313678Z",
          "volume_24h_usd": 3519
        },
        {
          "platform": "polymarket",
          "market_id": "559681",
          "market_url": "https://polymarket.com/event/democratic-presidential-nominee-2028/will-lebron-james-win-the-2028-democratic-presidential-nomination",
          "side": "YES",
          "price": 0.0075,
          "depth_usd_at_price": 692722,
          "last_trade_at": "2026-06-11T19:39:01.227545Z",
          "volume_24h_usd": 19295
        },
        {
          "platform": "polymarket",
          "market_id": "559682",
          "market_url": "https://polymarket.com/event/democratic-presidential-nominee-2028/will-person-a-win-the-2028-democratic-presidential-nomination",
          "side": "YES",
          "price": 0.0145,
          "depth_usd_at_price": 222261,
          "last_trade_at": "2026-06-11T19:42:50.557886Z",
          "volume_24h_usd": 12608
        },
        {
          "platform": "polymarket",
          "market_id": "559684",
          "market_url": "https://polymarket.com/event/democratic-presidential-nominee-2028/will-chelsea-clinton-win-the-2028-democratic-presidential-nomination",
          "side": "YES",
          "price": 0.0095,
          "depth_usd_at_price": 132200,
          "last_trade_at": "2026-06-11T19:38:39.312052Z",
          "volume_24h_usd": 3822
        },
        {
          "platform": "polymarket",
          "market_id": "559686",
          "market_url": "https://polymarket.com/event/democratic-presidential-nominee-2028/will-dwayne-the-rock-johnson-win-the-2028-democratic-presidential-nomination",
          "side": "YES",
          "price": 0.0125,
          "depth_usd_at_price": 59947,
          "last_trade_at": "2026-06-11T19:48:35.731064Z",
          "volume_24h_usd": 6460
        },
        {
          "platform": "polymarket",
          "market_id": "559685",
          "market_url": "https://polymarket.com/event/democratic-presidential-nominee-2028/will-mrbeast-win-the-2028-democratic-presidential-nomination",
          "side": "YES",
          "price": 0.0075,
          "depth_usd_at_price": 683752,
          "last_trade_at": "2026-06-11T19:38:35.336918Z",
          "volume_24h_usd": 21150
        },
        {
          "platform": "polymarket",
          "market_id": "559691",
          "market_url": "https://polymarket.com/event/democratic-presidential-nominee-2028/will-chris-murphy-win-the-2028-democratic-presidential-nomination",
          "side": "YES",
          "price": 0.0085,
          "depth_usd_at_price": 440741,
          "last_trade_at": "2026-06-11T19:42:00.032717Z",
          "volume_24h_usd": 32358
        },
        {
          "platform": "polymarket",
          "market_id": "559694",
          "market_url": "https://polymarket.com/event/democratic-presidential-nominee-2028/will-ro-khanna-win-the-2028-democratic-presidential-nomination",
          "side": "YES",
          "price": 0.0165,
          "depth_usd_at_price": 61318,
          "last_trade_at": "2026-06-11T19:39:14.881513Z",
          "volume_24h_usd": 3213
        },
        {
          "platform": "polymarket",
          "market_id": "559655",
          "market_url": "https://polymarket.com/event/democratic-presidential-nominee-2028/will-josh-shapiro-win-the-2028-democratic-presidential-nomination-977",
          "side": "YES",
          "price": 0.0535,
          "depth_usd_at_price": 103644,
          "last_trade_at": "2026-06-11T19:41:29.848602Z",
          "volume_24h_usd": 11634
        },
        {
          "platform": "polymarket",
          "market_id": "559672",
          "market_url": "https://polymarket.com/event/democratic-presidential-nominee-2028/will-roy-cooper-win-the-2028-democratic-presidential-nomination-286",
          "side": "YES",
          "price": 0.0095,
          "depth_usd_at_price": 381515,
          "last_trade_at": "2026-06-11T19:38:51.53489Z",
          "volume_24h_usd": 1582
        },
        {
          "platform": "polymarket",
          "market_id": "559692",
          "market_url": "https://polymarket.com/event/democratic-presidential-nominee-2028/will-jasmine-crockett-win-the-2028-democratic-presidential-nomination",
          "side": "YES",
          "price": 0.0065,
          "depth_usd_at_price": 651916,
          "last_trade_at": "2026-06-11T19:38:01.568661Z",
          "volume_24h_usd": 36715
        },
        {
          "platform": "polymarket",
          "market_id": "559696",
          "market_url": "https://polymarket.com/event/democratic-presidential-nominee-2028/will-graham-platner-win-the-2028-democratic-presidential-nomination",
          "side": "YES",
          "price": 0.0065,
          "depth_usd_at_price": 485507,
          "last_trade_at": "2026-06-11T19:42:45.496726Z",
          "volume_24h_usd": 33007
        },
        {
          "platform": "polymarket",
          "market_id": "559658",
          "market_url": "https://polymarket.com/event/democratic-presidential-nominee-2028/will-kamala-harris-win-the-2028-democratic-presidential-nomination-641",
          "side": "YES",
          "price": 0.0765,
          "depth_usd_at_price": 70754,
          "last_trade_at": "2026-06-11T19:42:34.203731Z",
          "volume_24h_usd": 4815
        },
        {
          "platform": "polymarket",
          "market_id": "559677",
          "market_url": "https://polymarket.com/event/democratic-presidential-nominee-2028/will-hillary-clinton-win-the-2028-democratic-presidential-nomination",
          "side": "YES",
          "price": 0.0075,
          "depth_usd_at_price": 410803,
          "last_trade_at": "2026-06-11T19:39:04.798392Z",
          "volume_24h_usd": 28207
        },
        {
          "platform": "polymarket",
          "market_id": "559652",
          "market_url": "https://polymarket.com/event/democratic-presidential-nominee-2028/will-gavin-newsom-win-the-2028-democratic-presidential-nomination-568",
          "side": "YES",
          "price": 0.2305,
          "depth_usd_at_price": 52099,
          "last_trade_at": "2026-06-11T19:47:27.100321Z",
          "volume_24h_usd": 16131
        }
      ],
      "edge_gross_pct": 3.05,
      "edge_net_estimate_pct": -25.83,
      "max_executable_size_per_leg_usd": 52099,
      "edge_net_per_dollar": -0.2583,
      "weakest_link_summary": "Net edge negative after fees at any size — sum violation exists but Polymarket fees + spread on 45 legs consume it.",
      "confidence_flags": [
        "low_volume"
      ],
      "persistence": {
        "first_seen_at": "2026-05-29T03:28:23.100Z",
        "scans_seen": 342,
        "hours_persisted": 328.36,
        "gross_pct_history": [
          3,
          3.05,
          3.05,
          3.05,
          3.05,
          3.05,
          3.05,
          3.05,
          3.05,
          3.05
        ],
        "trend": "stable"
      }
    },
    {
      "id": "pass1-poly-sum-republican-presidential-nominee-2028-underpriced",
      "tier": 3,
      "type": "poly_sum_violation",
      "summary": "Polymarket negRisk: Republican Presidential Nominee 2028 — 35 legs sum to 0.981 (1.9pp underpriced; buy-all-YES)",
      "underlying": "OTHER",
      "resolution_date": "2028-11-07",
      "resolution_type": "quarterly",
      "legs": [
        {
          "platform": "polymarket",
          "market_id": "561973",
          "market_url": "https://polymarket.com/event/republican-presidential-nominee-2028/will-donald-trump-win-the-2028-republican-presidential-nomination",
          "side": "YES",
          "price": 0.0205,
          "depth_usd_at_price": 92838,
          "last_trade_at": "2026-06-11T19:38:59.15682Z",
          "volume_24h_usd": 42107
        },
        {
          "platform": "polymarket",
          "market_id": "561974",
          "market_url": "https://polymarket.com/event/republican-presidential-nominee-2028/will-jd-vance-win-the-2028-republican-presidential-nomination",
          "side": "YES",
          "price": 0.3395,
          "depth_usd_at_price": 86579,
          "last_trade_at": "2026-06-11T19:37:35.036738Z",
          "volume_24h_usd": 11032
        },
        {
          "platform": "polymarket",
          "market_id": "562000",
          "market_url": "https://polymarket.com/event/republican-presidential-nominee-2028/will-rand-paul-win-the-2028-republican-presidential-nomination",
          "side": "YES",
          "price": 0.0095,
          "depth_usd_at_price": 374710,
          "last_trade_at": "2026-06-11T19:47:38.366229Z",
          "volume_24h_usd": 1648
        },
        {
          "platform": "polymarket",
          "market_id": "561975",
          "market_url": "https://polymarket.com/event/republican-presidential-nominee-2028/will-marco-rubio-win-the-2028-republican-presidential-nomination",
          "side": "YES",
          "price": 0.2295,
          "depth_usd_at_price": 43229,
          "last_trade_at": "2026-06-11T19:47:23.874246Z",
          "volume_24h_usd": 11837
        },
        {
          "platform": "polymarket",
          "market_id": "561976",
          "market_url": "https://polymarket.com/event/republican-presidential-nominee-2028/will-tulsi-gabbard-win-the-2028-republican-presidential-nomination",
          "side": "YES",
          "price": 0.0095,
          "depth_usd_at_price": 327035,
          "last_trade_at": "2026-06-11T19:39:55.743884Z",
          "volume_24h_usd": 705
        },
        {
          "platform": "polymarket",
          "market_id": "561977",
          "market_url": "https://polymarket.com/event/republican-presidential-nominee-2028/will-glenn-youngkin-win-the-2028-republican-presidential-nomination",
          "side": "YES",
          "price": 0.0135,
          "depth_usd_at_price": 74056,
          "last_trade_at": "2026-06-11T19:39:49.234028Z",
          "volume_24h_usd": 127
        },
        {
          "platform": "polymarket",
          "market_id": "562003",
          "market_url": "https://polymarket.com/event/republican-presidential-nominee-2028/will-kim-kardashian-win-the-2028-republican-presidential-nomination",
          "side": "YES",
          "price": 0.0085,
          "depth_usd_at_price": 531762,
          "last_trade_at": "2026-06-11T19:40:58.20874Z",
          "volume_24h_usd": 9749
        },
        {
          "platform": "polymarket",
          "market_id": "561978",
          "market_url": "https://polymarket.com/event/republican-presidential-nominee-2028/will-donald-trump-jr-win-the-2028-republican-presidential-nomination",
          "side": "YES",
          "price": 0.0255,
          "depth_usd_at_price": 128491,
          "last_trade_at": "2026-06-11T19:38:40.386761Z",
          "volume_24h_usd": 10304
        },
        {
          "platform": "polymarket",
          "market_id": "561991",
          "market_url": "https://polymarket.com/event/republican-presidential-nominee-2028/will-matt-gaetz-win-the-2028-republican-presidential-nomination",
          "side": "YES",
          "price": 0.0075,
          "depth_usd_at_price": 470375,
          "last_trade_at": "2026-06-11T19:47:29.473887Z",
          "volume_24h_usd": 18571
        },
        {
          "platform": "polymarket",
          "market_id": "561979",
          "market_url": "https://polymarket.com/event/republican-presidential-nominee-2028/will-ron-desantis-win-the-2028-republican-presidential-nomination",
          "side": "YES",
          "price": 0.0305,
          "depth_usd_at_price": 66060,
          "last_trade_at": "2026-06-11T19:39:01.254807Z",
          "volume_24h_usd": 13025
        },
        {
          "platform": "polymarket",
          "market_id": "562004",
          "market_url": "https://polymarket.com/event/republican-presidential-nominee-2028/will-marjorie-taylor-greene-win-the-2028-republican-presidential-nomination",
          "side": "YES",
          "price": 0.0095,
          "depth_usd_at_price": 269046,
          "last_trade_at": "2026-06-11T19:48:00.245588Z",
          "volume_24h_usd": 5852
        },
        {
          "platform": "polymarket",
          "market_id": "561980",
          "market_url": "https://polymarket.com/event/republican-presidential-nominee-2028/will-nikki-haley-win-the-2028-republican-presidential-nomination",
          "side": "YES",
          "price": 0.0085,
          "depth_usd_at_price": 312946,
          "last_trade_at": "2026-06-11T19:39:54.501828Z",
          "volume_24h_usd": 15878
        },
        {
          "platform": "polymarket",
          "market_id": "561981",
          "market_url": "https://polymarket.com/event/republican-presidential-nominee-2028/will-vivek-ramaswamy-win-the-2028-republican-presidential-nomination",
          "side": "YES",
          "price": 0.0125,
          "depth_usd_at_price": 278623,
          "last_trade_at": "2026-06-11T19:37:42.132531Z",
          "volume_24h_usd": 17149
        },
        {
          "platform": "polymarket",
          "market_id": "562006",
          "market_url": "https://polymarket.com/event/republican-presidential-nominee-2028/will-eric-trump-win-the-2028-republican-presidential-nomination",
          "side": "YES",
          "price": 0.0075,
          "depth_usd_at_price": 483826,
          "last_trade_at": "2026-06-11T19:42:24.887633Z",
          "volume_24h_usd": 20041
        },
        {
          "platform": "polymarket",
          "market_id": "561982",
          "market_url": "https://polymarket.com/event/republican-presidential-nominee-2028/will-sarah-huckabee-sanders-win-the-2028-republican-presidential-nomination",
          "side": "YES",
          "price": 0.0075,
          "depth_usd_at_price": 462403,
          "last_trade_at": "2026-06-11T19:38:40.906881Z",
          "volume_24h_usd": 26239
        },
        {
          "platform": "polymarket",
          "market_id": "561983",
          "market_url": "https://polymarket.com/event/republican-presidential-nominee-2028/will-greg-abbott-win-the-2028-republican-presidential-nomination",
          "side": "YES",
          "price": 0.0175,
          "depth_usd_at_price": 379410,
          "last_trade_at": "2026-06-11T19:37:34.260379Z",
          "volume_24h_usd": 1399
        },
        {
          "platform": "polymarket",
          "market_id": "562008",
          "market_url": "https://polymarket.com/event/republican-presidential-nominee-2028/will-pete-hegseth-win-the-2028-republican-presidential-nomination",
          "side": "YES",
          "price": 0.0075,
          "depth_usd_at_price": 436017,
          "last_trade_at": "2026-06-11T19:48:07.215348Z",
          "volume_24h_usd": 32077
        },
        {
          "platform": "polymarket",
          "market_id": "561984",
          "market_url": "https://polymarket.com/event/republican-presidential-nominee-2028/will-robert-f-kennedy-jr-win-the-2028-republican-presidential-nomination",
          "side": "YES",
          "price": 0.0085,
          "depth_usd_at_price": 425850,
          "last_trade_at": "2026-06-11T19:39:16.802775Z",
          "volume_24h_usd": 24694
        },
        {
          "platform": "polymarket",
          "market_id": "561996",
          "market_url": "https://polymarket.com/event/republican-presidential-nominee-2028/will-tucker-carlson-win-the-2028-republican-presidential-nomination",
          "side": "YES",
          "price": 0.0645,
          "depth_usd_at_price": 51102,
          "last_trade_at": "2026-06-11T19:48:45.275175Z",
          "volume_24h_usd": 12343
        },
        {
          "platform": "polymarket",
          "market_id": "561985",
          "market_url": "https://polymarket.com/event/republican-presidential-nominee-2028/will-brian-kemp-win-the-2028-republican-presidential-nomination",
          "side": "YES",
          "price": 0.0085,
          "depth_usd_at_price": 254077,
          "last_trade_at": "2026-06-11T19:42:17.014467Z",
          "volume_24h_usd": 19605
        },
        {
          "platform": "polymarket",
          "market_id": "561986",
          "market_url": "https://polymarket.com/event/republican-presidential-nominee-2028/will-byron-donalds-win-the-2028-republican-presidential-nomination",
          "side": "YES",
          "price": 0.0075,
          "depth_usd_at_price": 408315,
          "last_trade_at": "2026-06-11T19:39:37.047754Z",
          "volume_24h_usd": 312049
        },
        {
          "platform": "polymarket",
          "market_id": "561998",
          "market_url": "https://polymarket.com/event/republican-presidential-nominee-2028/will-ivanka-trump-win-the-2028-republican-presidential-nomination",
          "side": "YES",
          "price": 0.0105,
          "depth_usd_at_price": 192569,
          "last_trade_at": "2026-06-11T19:38:27.77754Z",
          "volume_24h_usd": 407
        },
        {
          "platform": "polymarket",
          "market_id": "561987",
          "market_url": "https://polymarket.com/event/republican-presidential-nominee-2028/will-elise-stefanik-win-the-2028-republican-presidential-nomination",
          "side": "YES",
          "price": 0.0075,
          "depth_usd_at_price": 508575,
          "last_trade_at": "2026-06-11T19:42:33.566932Z",
          "volume_24h_usd": 24743
        },
        {
          "platform": "polymarket",
          "market_id": "561988",
          "market_url": "https://polymarket.com/event/republican-presidential-nominee-2028/will-josh-hawley-win-the-2028-republican-presidential-nomination",
          "side": "YES",
          "price": 0.0085,
          "depth_usd_at_price": 220919,
          "last_trade_at": "2026-06-11T19:42:28.552022Z",
          "volume_24h_usd": 16022
        },
        {
          "platform": "polymarket",
          "market_id": "561989",
          "market_url": "https://polymarket.com/event/republican-presidential-nominee-2028/will-ted-cruz-win-the-2028-republican-presidential-nomination",
          "side": "YES",
          "price": 0.0095,
          "depth_usd_at_price": 300412,
          "last_trade_at": "2026-06-11T19:47:09.562596Z",
          "volume_24h_usd": 2632
        },
        {
          "platform": "polymarket",
          "market_id": "561990",
          "market_url": "https://polymarket.com/event/republican-presidential-nominee-2028/will-elon-musk-win-the-2028-republican-presidential-nomination",
          "side": "YES",
          "price": 0.0095,
          "depth_usd_at_price": 470674,
          "last_trade_at": "2026-06-11T19:37:28.933879Z",
          "volume_24h_usd": 2029
        },
        {
          "platform": "polymarket",
          "market_id": "562002",
          "market_url": "https://polymarket.com/event/republican-presidential-nominee-2028/will-erika-kirk-win-the-2028-republican-presidential-nomination",
          "side": "YES",
          "price": 0.0075,
          "depth_usd_at_price": 481138,
          "last_trade_at": "2026-06-11T19:39:22.137363Z",
          "volume_24h_usd": 21201
        },
        {
          "platform": "polymarket",
          "market_id": "561992",
          "market_url": "https://polymarket.com/event/republican-presidential-nominee-2028/will-katie-britt-win-the-2028-republican-presidential-nomination",
          "side": "YES",
          "price": 0.0085,
          "depth_usd_at_price": 495471,
          "last_trade_at": "2026-06-11T19:38:39.851474Z",
          "volume_24h_usd": 10474
        },
        {
          "platform": "polymarket",
          "market_id": "562005",
          "market_url": "https://polymarket.com/event/republican-presidential-nominee-2028/will-thomas-massie-win-the-2028-republican-presidential-nomination",
          "side": "YES",
          "price": 0.0215,
          "depth_usd_at_price": 64194,
          "last_trade_at": "2026-06-11T19:47:31.299925Z",
          "volume_24h_usd": 8806
        },
        {
          "platform": "polymarket",
          "market_id": "561993",
          "market_url": "https://polymarket.com/event/republican-presidential-nominee-2028/will-john-thune-win-the-2028-republican-presidential-nomination",
          "side": "YES",
          "price": 0.0075,
          "depth_usd_at_price": 498087,
          "last_trade_at": "2026-06-11T19:42:31.529836Z",
          "volume_24h_usd": 28281
        },
        {
          "platform": "polymarket",
          "market_id": "561994",
          "market_url": "https://polymarket.com/event/republican-presidential-nominee-2028/will-kristi-noem-win-the-2028-republican-presidential-nomination",
          "side": "YES",
          "price": 0.0065,
          "depth_usd_at_price": 439526,
          "last_trade_at": "2026-06-11T19:39:13.639895Z",
          "volume_24h_usd": 32034
        },
        {
          "platform": "polymarket",
          "market_id": "562007",
          "market_url": "https://polymarket.com/event/republican-presidential-nominee-2028/will-joe-kent-win-the-2028-republican-presidential-nomination",
          "side": "YES",
          "price": 0.0075,
          "depth_usd_at_price": 316000,
          "last_trade_at": "2026-06-11T19:37:32.378852Z",
          "volume_24h_usd": 22020
        },
        {
          "platform": "polymarket",
          "market_id": "561995",
          "market_url": "https://polymarket.com/event/republican-presidential-nominee-2028/will-mike-pence-win-the-2028-republican-presidential-nomination",
          "side": "YES",
          "price": 0.0065,
          "depth_usd_at_price": 482819,
          "last_trade_at": "2026-06-11T19:47:35.382674Z",
          "volume_24h_usd": 20492
        },
        {
          "platform": "polymarket",
          "market_id": "561999",
          "market_url": "https://polymarket.com/event/republican-presidential-nominee-2028/will-tom-brady-win-the-2028-republican-presidential-nomination",
          "side": "YES",
          "price": 0.0085,
          "depth_usd_at_price": 485693,
          "last_trade_at": "2026-06-11T19:39:13.657779Z",
          "volume_24h_usd": 9547
        },
        {
          "platform": "polymarket",
          "market_id": "562001",
          "market_url": "https://polymarket.com/event/republican-presidential-nominee-2028/will-steve-bannon-win-the-2028-republican-presidential-nomination",
          "side": "YES",
          "price": 0.0085,
          "depth_usd_at_price": 459382,
          "last_trade_at": "2026-06-11T19:42:06.5215Z",
          "volume_24h_usd": 8365
        }
      ],
      "edge_gross_pct": 1.85,
      "edge_net_estimate_pct": -26.2,
      "max_executable_size_per_leg_usd": 43229,
      "edge_net_per_dollar": -0.262,
      "weakest_link_summary": "Net edge negative after fees at any size — sum violation exists but Polymarket fees + spread on 35 legs consume it.",
      "confidence_flags": [
        "low_volume"
      ],
      "persistence": {
        "first_seen_at": "2026-06-02T04:30:47.167Z",
        "scans_seen": 587,
        "hours_persisted": 231.32,
        "gross_pct_history": [
          1.65,
          1.65,
          1.6,
          1.55,
          1.55,
          1.55,
          1.5,
          1.5,
          1.5,
          1.85
        ],
        "trend": "stable"
      }
    }
  ],
  "track_record": {
    "lookback_days": 14,
    "total_observed": 559,
    "active": 9,
    "left_feed": 550,
    "among_active": {
      "closed_substantially": 0,
      "tightened": 1,
      "stable": 3,
      "widened": 5
    },
    "among_active_pct": {
      "closed_substantially": 0,
      "tightened": 11.1,
      "stable": 33.3,
      "widened": 55.6
    },
    "left_feed_reasons": {
      "leg_expired": 138,
      "leg_delisted": 287,
      "spread_closed": 125,
      "unknown": 0
    },
    "median_lifetime_hours": 0.25,
    "by_tier": {
      "1": {
        "total_observed": 2,
        "active": 0,
        "left_feed": 2,
        "among_active": {
          "closed_substantially": 0,
          "tightened": 0,
          "stable": 0,
          "widened": 0
        },
        "left_feed_reasons": {
          "leg_expired": 0,
          "leg_delisted": 2,
          "spread_closed": 0,
          "unknown": 0
        }
      },
      "2": {
        "total_observed": 10,
        "active": 2,
        "left_feed": 8,
        "among_active": {
          "closed_substantially": 0,
          "tightened": 0,
          "stable": 0,
          "widened": 2
        },
        "left_feed_reasons": {
          "leg_expired": 0,
          "leg_delisted": 6,
          "spread_closed": 2,
          "unknown": 0
        }
      },
      "3": {
        "total_observed": 547,
        "active": 7,
        "left_feed": 540,
        "among_active": {
          "closed_substantially": 0,
          "tightened": 1,
          "stable": 3,
          "widened": 3
        },
        "left_feed_reasons": {
          "leg_expired": 138,
          "leg_delisted": 279,
          "spread_closed": 123,
          "unknown": 0
        }
      }
    }
  }
}
